spectranormalizer/__init__.py
spectranormalizer/nomad_plugin.yaml
spectranormalizer/normalizer.py
nomad_normalizer_plugin_spectra-1.0.3.dist-info/LICENSE
nomad_normalizer_plugin_spectra-1.0.3.dist-info/METADATA
nomad_normalizer_plugin_spectra-1.0.3.dist-info/WHEEL
nomad_normalizer_plugin_spectra-1.0.3.dist-info/entry_points.txt
nomad_normalizer_plugin_spectra-1.0.3.dist-info/top_level.txt
nomad_normalizer_plugin_spectra-1.0.3.dist-info/RECORD
